creaap/__init__.py
creaap/formats.py
creaap/io.py
creaap/models.py
creaap/utils.py
creaap/spatial/__init__.py
creaap/spatial/match.py
creaap/spatial/utils.py
creaap/spatial/data/nuts0
creaap/spatial/data/nuts1
creaap/spatial/data/nuts2
creaap/spatial/data/nuts3
creaap/storage/__init__.py
creaap/storage/blob.py
creaap/storage/file.py
creaap/storage/table.py
creaap/users/__init__.py
creaap/users/aad.py
creaap-0.1.15.dist-info/LICENSE
creaap-0.1.15.dist-info/METADATA
creaap-0.1.15.dist-info/WHEEL
creaap-0.1.15.dist-info/top_level.txt
creaap-0.1.15.dist-info/RECORD
