Metadata-Version: 2.1
Name: creaap
Version: 0.1.15
Summary: CREA Applications in Python toolkit. A bundle of tools to speed up the deelopment of new Python applications in Azure. Allows you to abstract a little over persistence and to manage spatial data.
Home-page: https://dev.azure.com/dariodenart/_git/CREA%20Application%20Python%20toolkit
Author: CREA
Author-email: dario.denart@crea.gov.it
Classifier: Programming Language :: Python :: 3
Classifier: Programming Language :: Python :: 3.7
Classifier: Programming Language :: Python :: 3.8
Classifier: Programming Language :: Python :: 3.9
Classifier: Programming Language :: Python :: 3.10
Classifier: Programming Language :: Python :: 3.11
Classifier: Programming Language :: Python :: 3.12
Classifier: Topic :: Software Development :: Libraries :: Python Modules
Classifier: License :: OSI Approved :: MIT License
Classifier: Operating System :: OS Independent
License-File: LICENSE
Requires-Dist: azure-storage-blob
Requires-Dist: azure-storage-file-share
Requires-Dist: azure-data-tables
Requires-Dist: Shapely>=2.0.0
Requires-Dist: pytz
Requires-Dist: pygeoif
Requires-Dist: numpy
Requires-Dist: scipy
Requires-Dist: scikit-learn
Requires-Dist: pyshp
Requires-Dist: pandas
Requires-Dist: pyproj
Requires-Dist: msal
